clarku_niulabtesting2/__init__.py
clarku_niulabtesting2/_check_sum.py
clarku_niulabtesting2-0.0.1.dist-info/LICENSE.txt
clarku_niulabtesting2-0.0.1.dist-info/METADATA
clarku_niulabtesting2-0.0.1.dist-info/WHEEL
clarku_niulabtesting2-0.0.1.dist-info/top_level.txt
clarku_niulabtesting2-0.0.1.dist-info/RECORD
