Metadata-Version: 2.1
Name: clarku-niulabtesting2
Version: 0.0.1
Summary: Example package for Youtube crawler
Home-page: https://github.com/pypa/sampleproject
Maintainer: Cat Mai
Maintainer-email: CMai@clarku.edu
License: UNKNOWN
Platform: UNKNOWN
Classifier: Programming Language :: Python :: 3
Classifier: License :: OSI Approved :: MIT License
Classifier: Operating System :: OS Independent
Requires-Python: >=3.6
